gomask/__init__.py
gomask/api/__init__.py
gomask/api/client.py
gomask/api/connectors.py
gomask/api/execution.py
gomask/api/functions.py
gomask/api/routines.py
gomask/auth/__init__.py
gomask/auth/middleware.py
gomask/auth/secret.py
gomask/cli.py
gomask/commands/__init__.py
gomask/commands/connectors.py
gomask/commands/example.py
gomask/commands/executions.py
gomask/commands/export.py
gomask/commands/functions.py
gomask/commands/import_cmd.py
gomask/commands/init.py
gomask/commands/routines.py
gomask/commands/run.py
gomask/commands/setup.py
gomask/commands/validate.py
gomask/parser/__init__.py
gomask/parser/export.py
gomask/parser/yaml_parser.py
gomask/schema/README.md
gomask/schema/__init__.py
gomask/schema/defaults.py
gomask/schema/masking-routine-schema.json
gomask/schema/models.py
gomask/schema/synthetic-routine-schema.json
gomask/schema/unified-routine-schema.json
gomask/schema/validator.py
gomask/utils/__init__.py
gomask/utils/config.py
gomask/utils/credits.py
gomask/utils/hash.py
gomask/utils/logger.py
gomask/utils/output.py
gomask/validators.py
gomask_cli-1.0.0.dist-info/METADATA
gomask_cli-1.0.0.dist-info/WHEEL
gomask_cli-1.0.0.dist-info/entry_points.txt
gomask_cli-1.0.0.dist-info/RECORD
